{
  "last_update": 1764593721603,
  "rates": {
    "KRW": 1,
    "AED": 0.002504,
    "AFN": 0.04507,
    "ALL": 0.05676,
    "AMD": 0.2593,
    "ANG": 0.00122,
    "AOA": 0.6281,
    "ARS": 0.9892,
    "AUD": 0.001041,
    "AWG": 0.00122,
    "AZN": 0.001157,
    "BAM": 0.00115,
    "BBD": 0.001364,
    "BDT": 0.08278,
    "BGN": 0.00115,
    "BHD": 0.00025636,
    "BIF": 2,
    "BMD": 0.00068182,
    "BND": 0.00088353,
    "BOB": 0.004707,
    "BRL": 0.003631,
    "BSD": 0.00068182,
    "BTN": 0.061,
    "BWP": 0.009439,
    "BYN": 0.002293,
    "BZD": 0.001364,
    "CAD": 0.00095157,
    "CDF": 1.5522,
    "CHF": 0.00054718,
    "CLF": 0.00001597,
    "CLP": 0.6313,
    "CNH": 0.004811,
    "CNY": 0.004836,
    "COP": 2.5454,
    "CRC": 0.3381,
    "CUP": 0.01636,
    "CVE": 0.06481,
    "CZK": 0.01419,
    "DJF": 0.1212,
    "DKK": 0.004385,
    "DOP": 0.04262,
    "DZD": 0.08877,
    "EGP": 0.03237,
    "ERN": 0.01023,
    "ETB": 0.1044,
    "EUR": 0.00058712,
    "FJD": 0.001548,
    "FKP": 0.00051507,
    "FOK": 0.004384,
    "GBP": 0.00051423,
    "GEL": 0.001836,
    "GGP": 0.00051507,
    "GHS": 0.007668,
    "GIP": 0.00051507,
    "GMD": 0.05044,
    "GNF": 5.938,
    "GTQ": 0.005213,
    "GYD": 0.1423,
    "HKD": 0.005295,
    "HNL": 0.01791,
    "HRK": 0.004429,
    "HTG": 0.08893,
    "HUF": 0.2239,
    "IDR": 11.3455,
    "ILS": 0.002222,
    "IMP": 0.00051507,
    "INR": 0.06094,
    "IQD": 0.8889,
    "IRR": 29.5353,
    "ISK": 0.08709,
    "JEP": 0.00051507,
    "JMD": 0.109,
    "JOD": 0.00048341,
    "JPY": 0.1062,
    "KES": 0.08815,
    "KGS": 0.05946,
    "KHR": 2.7368,
    "KID": 0.001042,
    "KMF": 0.2892,
    "KWD": 0.00020662,
    "KYD": 0.00056818,
    "KZT": 0.3483,
    "LAK": 14.7795,
    "LBP": 61.0229,
    "LKR": 0.2091,
    "LRD": 0.1207,
    "LSL": 0.01165,
    "LYD": 0.003706,
    "MAD": 0.006311,
    "MDL": 0.01158,
    "MGA": 3.0588,
    "MKD": 0.03632,
    "MMK": 1.4277,
    "MNT": 2.4359,
    "MOP": 0.005454,
    "MRU": 0.02713,
    "MUR": 0.03178,
    "MVR": 0.01051,
    "MWK": 1.1833,
    "MXN": 0.01247,
    "MYR": 0.002811,
    "MZN": 0.0433,
    "NAD": 0.01165,
    "NGN": 0.9832,
    "NIO": 0.02504,
    "NOK": 0.00691,
    "NPR": 0.0976,
    "NZD": 0.001191,
    "OMR": 0.00026216,
    "PAB": 0.00068182,
    "PEN": 0.00229,
    "PGK": 0.002921,
    "PHP": 0.03995,
    "PKR": 0.1922,
    "PLN": 0.002491,
    "PYG": 4.7428,
    "QAR": 0.002482,
    "RON": 0.002994,
    "RSD": 0.06898,
    "RUB": 0.05273,
    "RWF": 0.9914,
    "SAR": 0.002557,
    "SBD": 0.00561,
    "SCR": 0.009848,
    "SDG": 0.3041,
    "SEK": 0.006456,
    "SGD": 0.00088214,
    "SHP": 0.00051507,
    "SLE": 0.01456,
    "SLL": 14.5764,
    "SOS": 0.3881,
    "SRD": 0.02612,
    "SSP": 3.213,
    "STN": 0.0144,
    "SYP": 7.4918,
    "SZL": 0.01165,
    "THB": 0.02186,
    "TJS": 0.006308,
    "TMT": 0.00238,
    "TND": 0.002003,
    "TOP": 0.00164,
    "TRY": 0.02891,
    "TTD": 0.004625,
    "TVD": 0.001042,
    "TWD": 0.02141,
    "TZS": 1.6792,
    "UAH": 0.02876,
    "UGX": 2.4757,
    "USD": 0.00068125,
    "UYU": 0.02699,
    "UZS": 8.0175,
    "VES": 0.1685,
    "VND": 17.8465,
    "VUV": 0.08343,
    "WST": 0.001917,
    "XAF": 0.3856,
    "XCD": 0.001841,
    "XCG": 0.00122,
    "XDR": 0.00049987,
    "XOF": 0.3856,
    "XPF": 0.07014,
    "YER": 0.1623,
    "ZAR": 0.01165,
    "ZMW": 0.01562,
    "ZWG": 0.01786,
    "ZWL": 0.01784
  }
}