{
  "last_update": 1765505079172,
  "rates": {
    "KRW": 1,
    "AED": 0.002497,
    "AFN": 0.04479,
    "ALL": 0.05608,
    "AMD": 0.2591,
    "ANG": 0.001217,
    "AOA": 0.638,
    "ARS": 0.978,
    "AUD": 0.00102,
    "AWG": 0.001217,
    "AZN": 0.001153,
    "BAM": 0.001134,
    "BBD": 0.00136,
    "BDT": 0.08289,
    "BGN": 0.001134,
    "BHD": 0.00025568,
    "BIF": 2.0097,
    "BMD": 0.00068,
    "BND": 0.00087873,
    "BOB": 0.004697,
    "BRL": 0.003706,
    "BSD": 0.00068,
    "BTN": 0.06141,
    "BWP": 0.009349,
    "BYN": 0.001971,
    "BZD": 0.00136,
    "CAD": 0.00093682,
    "CDF": 1.5564,
    "CHF": 0.00054107,
    "CLF": 0.00001585,
    "CLP": 0.6263,
    "CNH": 0.004795,
    "CNY": 0.004807,
    "COP": 2.5996,
    "CRC": 0.3366,
    "CUP": 0.01632,
    "CVE": 0.06393,
    "CZK": 0.01405,
    "DJF": 0.1209,
    "DKK": 0.004325,
    "DOP": 0.04343,
    "DZD": 0.08814,
    "EGP": 0.03227,
    "ERN": 0.0102,
    "ETB": 0.1055,
    "EUR": 0.00057963,
    "FJD": 0.001543,
    "FKP": 0.00050764,
    "FOK": 0.004324,
    "GBP": 0.00050747,
    "GEL": 0.001831,
    "GGP": 0.00050764,
    "GHS": 0.007938,
    "GIP": 0.00050764,
    "GMD": 0.05038,
    "GNF": 5.9152,
    "GTQ": 0.005188,
    "GYD": 0.1417,
    "HKD": 0.005288,
    "HNL": 0.01784,
    "HRK": 0.004368,
    "HTG": 0.08869,
    "HUF": 0.2222,
    "IDR": 11.3201,
    "ILS": 0.002182,
    "IMP": 0.00050764,
    "INR": 0.06139,
    "IQD": 0.8884,
    "IRR": 28.9677,
    "ISK": 0.08623,
    "JEP": 0.00050764,
    "JMD": 0.1085,
    "JOD": 0.00048212,
    "JPY": 0.1057,
    "KES": 0.08767,
    "KGS": 0.05924,
    "KHR": 2.7237,
    "KID": 0.001021,
    "KMF": 0.2852,
    "KWD": 0.00020639,
    "KYD": 0.00056667,
    "KZT": 0.3531,
    "LAK": 14.7075,
    "LBP": 60.8604,
    "LKR": 0.2093,
    "LRD": 0.1198,
    "LSL": 0.01149,
    "LYD": 0.003687,
    "MAD": 0.006242,
    "MDL": 0.01151,
    "MGA": 3,
    "MKD": 0.036,
    "MMK": 1.4265,
    "MNT": 2.385,
    "MOP": 0.005449,
    "MRU": 0.02711,
    "MUR": 0.03157,
    "MVR": 0.01048,
    "MWK": 1.1845,
    "MXN": 0.01232,
    "MYR": 0.002793,
    "MZN": 0.04339,
    "NAD": 0.01149,
    "NGN": 0.9856,
    "NIO": 0.02494,
    "NOK": 0.006855,
    "NPR": 0.09826,
    "NZD": 0.00117,
    "OMR": 0.00026146,
    "PAB": 0.00068,
    "PEN": 0.002286,
    "PGK": 0.002876,
    "PHP": 0.0401,
    "PKR": 0.1906,
    "PLN": 0.00245,
    "PYG": 4.667,
    "QAR": 0.002475,
    "RON": 0.002953,
    "RSD": 0.0682,
    "RUB": 0.05402,
    "RWF": 0.9917,
    "SAR": 0.00255,
    "SBD": 0.00552,
    "SCR": 0.009593,
    "SDG": 0.3026,
    "SEK": 0.006287,
    "SGD": 0.00087846,
    "SHP": 0.00050764,
    "SLE": 0.01638,
    "SLL": 16.3876,
    "SOS": 0.3862,
    "SRD": 0.02609,
    "SSP": 3.2118,
    "STN": 0.01421,
    "SYP": 7.4666,
    "SZL": 0.01149,
    "THB": 0.02158,
    "TJS": 0.006283,
    "TMT": 0.002376,
    "TND": 0.001971,
    "TOP": 0.001635,
    "TRY": 0.02897,
    "TTD": 0.004596,
    "TVD": 0.001021,
    "TWD": 0.02121,
    "TZS": 1.6754,
    "UAH": 0.02873,
    "UGX": 2.4137,
    "USD": 0.00067981,
    "UYU": 0.02653,
    "UZS": 8.2182,
    "VES": 0.182,
    "VND": 17.8174,
    "VUV": 0.08298,
    "WST": 0.001881,
    "XAF": 0.3803,
    "XCD": 0.001836,
    "XCG": 0.001217,
    "XDR": 0.00049383,
    "XOF": 0.3803,
    "XPF": 0.06919,
    "YER": 0.1618,
    "ZAR": 0.01149,
    "ZMW": 0.01576,
    "ZWG": 0.01776,
    "ZWL": 0.01775
  }
}