{
  "last_update": 1768222783272,
  "rates": {
    "KRW": 1,
    "AED": 0.002517,
    "AFN": 0.04528,
    "ALL": 0.05687,
    "AMD": 0.2618,
    "ANG": 0.001227,
    "AOA": 0.6344,
    "ARS": 0.9955,
    "AUD": 0.001025,
    "AWG": 0.001227,
    "AZN": 0.001166,
    "BAM": 0.001152,
    "BBD": 0.001371,
    "BDT": 0.08373,
    "BGN": 22.9462,
    "BHD": 0.00025774,
    "BIF": 2.0388,
    "BMD": 0.00068547,
    "BND": 0.00088215,
    "BOB": 0.004757,
    "BRL": 0.00369,
    "BSD": 0.00068547,
    "BTN": 0.06193,
    "BWP": 0.009369,
    "BYN": 0.002009,
    "BZD": 0.001371,
    "CAD": 0.00095282,
    "CDF": 1.4789,
    "CHF": 0.00054903,
    "CLF": 0.00001555,
    "CLP": 0.6147,
    "CNH": 0.004783,
    "CNY": 0.00481,
    "COP": 2.5516,
    "CRC": 0.3411,
    "CUP": 0.01645,
    "CVE": 0.06496,
    "CZK": 0.01432,
    "DJF": 0.1218,
    "DKK": 0.004395,
    "DOP": 0.04355,
    "DZD": 0.08922,
    "EGP": 0.03236,
    "ERN": 0.01028,
    "ETB": 0.1069,
    "EUR": 0.00058909,
    "FJD": 0.001561,
    "FKP": 0.00051135,
    "FOK": 0.0044,
    "GBP": 0.00051135,
    "GEL": 0.001851,
    "GGP": 0.00051135,
    "GHS": 0.007365,
    "GIP": 0.00051135,
    "GMD": 0.05073,
    "GNF": 6.0014,
    "GTQ": 0.00526,
    "GYD": 0.1436,
    "HKD": 0.005342,
    "HNL": 0.01809,
    "HRK": 0.004438,
    "HTG": 0.08986,
    "HUF": 0.2272,
    "IDR": 11.5346,
    "ILS": 0.00216,
    "IMP": 0.00051135,
    "INR": 0.06193,
    "IQD": 0.9013,
    "IRR": 29.0506,
    "ISK": 0.08684,
    "JEP": 0.00051135,
    "JMD": 0.1088,
    "JOD": 0.000486,
    "JPY": 0.1082,
    "KES": 0.08846,
    "KGS": 0.06003,
    "KHR": 2.7632,
    "KID": 0.001025,
    "KMF": 0.2898,
    "KWD": 0.00020949,
    "KYD": 0.00057123,
    "KZT": 0.3498,
    "LAK": 14.8864,
    "LBP": 61.3497,
    "LKR": 0.2116,
    "LRD": 0.123,
    "LSL": 0.01134,
    "LYD": 0.003725,
    "MAD": 0.006338,
    "MDL": 0.01153,
    "MGA": 3.1343,
    "MKD": 0.03619,
    "MMK": 1.439,
    "MNT": 2.4395,
    "MOP": 0.005502,
    "MRU": 0.02748,
    "MUR": 0.03201,
    "MVR": 0.0106,
    "MWK": 1.1945,
    "MXN": 0.01235,
    "MYR": 0.002796,
    "MZN": 0.04371,
    "NAD": 0.01134,
    "NGN": 0.9767,
    "NIO": 0.02524,
    "NOK": 0.006929,
    "NPR": 0.09909,
    "NZD": 0.001197,
    "OMR": 0.00026356,
    "PAB": 0.00068547,
    "PEN": 0.002307,
    "PGK": 0.002929,
    "PHP": 0.04063,
    "PKR": 0.1922,
    "PLN": 0.00248,
    "PYG": 4.5256,
    "QAR": 0.002495,
    "RON": 0.002996,
    "RSD": 0.06912,
    "RUB": 0.05413,
    "RWF": 1.0008,
    "SAR": 0.002571,
    "SBD": 0.005587,
    "SCR": 0.0102,
    "SDG": 0.307,
    "SEK": 0.006324,
    "SGD": 0.00088215,
    "SHP": 0.00051135,
    "SLE": 0.01634,
    "SLL": 16.3393,
    "SOS": 0.3918,
    "SRD": 0.02615,
    "SSP": 3.2412,
    "STN": 0.01443,
    "SYP": 0.07705,
    "SZL": 0.01134,
    "THB": 0.02152,
    "TJS": 0.006327,
    "TMT": 0.002399,
    "TND": 0.001983,
    "TOP": 0.001651,
    "TRY": 0.02955,
    "TTD": 0.004654,
    "TVD": 0.001025,
    "TWD": 0.02174,
    "TZS": 1.7242,
    "UAH": 0.02957,
    "UGX": 2.4711,
    "USD": 0.00068547,
    "UYU": 0.02676,
    "UZS": 8.3864,
    "VES": 0.2265,
    "VND": 17.8601,
    "VUV": 0.08289,
    "WST": 0.0019,
    "XAF": 0.3864,
    "XCD": 0.001851,
    "XCG": 0.001227,
    "XDR": 0.00050113,
    "XOF": 0.3864,
    "XPF": 0.0703,
    "YER": 0.1635,
    "ZAR": 0.01134,
    "ZMW": 0.01334,
    "ZWG": 0.01763,
    "ZWL": 0.01763
  }
}